moxn_types/__init__.py
moxn_types/auth.py
moxn_types/base.py
moxn_types/content.py
moxn_types/dto.py
moxn_types/exceptions.py
moxn_types/py.typed
moxn_types/request_config.py
moxn_types/requests.py
moxn_types/response.py
moxn_types/responses.py
moxn_types/schema.py
moxn_types/sentinel.py
moxn_types/telemetry.py
moxn_types/utils.py
moxn_types/blocks/base.py
moxn_types/blocks/block_converter.py
moxn_types/blocks/content_block.py
moxn_types/blocks/context.py
moxn_types/blocks/file.py
moxn_types/blocks/image.py
moxn_types/blocks/raw_block.py
moxn_types/blocks/signed.py
moxn_types/blocks/text.py
moxn_types/blocks/tool.py
moxn_types/blocks/typed_blocks.py
moxn_types/blocks/variable.py
moxn_types/type_aliases/.ruff.toml
moxn_types/type_aliases/anthropic.py
moxn_types/type_aliases/google.py
moxn_types/type_aliases/openai_chat.py
moxn_types/type_aliases/openai_responses.py
moxn_types/type_aliases/provider.py
moxn_types-0.0.0.27.dist-info/METADATA
moxn_types-0.0.0.27.dist-info/WHEEL
moxn_types-0.0.0.27.dist-info/RECORD
