Metadata-Version: 2.4
Name: moxn-types
Version: 0.0.0.27
Summary: Shared DTOs for the Moxn SDK and API
Author-email: Mark Weiss <mark@moxn.dev>
Requires-Python: >=3.11
Requires-Dist: pydantic>=2.9
Provides-Extra: anthropic
Requires-Dist: anthropic>=0.51.0; extra == 'anthropic'
Provides-Extra: google
Requires-Dist: google-genai>=1.16.1; extra == 'google'
Provides-Extra: openai
Requires-Dist: openai>=1.79.0; extra == 'openai'
